mrweb/__init__.py
mrweb/ai.py
mrweb/api.py
mrweb/exceptions.py
mrweb/fakemail.py
mrweb/hashcheck.py
mrweb/tron.py
mrweb-1.9.dist-info/METADATA
mrweb-1.9.dist-info/WHEEL
mrweb-1.9.dist-info/top_level.txt
mrweb-1.9.dist-info/RECORD
